.gitignore
LICENSE
README.md
pyproject.toml
uv.lock
.github/workflows/release.yml
.github/workflows/test.yaml
ommx_dwave_adapter/__init__.py
ommx_dwave_adapter/_version.py
ommx_dwave_adapter/adapter.py
ommx_dwave_adapter/exception.py
ommx_dwave_adapter.egg-info/PKG-INFO
ommx_dwave_adapter.egg-info/SOURCES.txt
ommx_dwave_adapter.egg-info/dependency_links.txt
ommx_dwave_adapter.egg-info/requires.txt
ommx_dwave_adapter.egg-info/top_level.txt
tests/test_cqm_adapter.py