Metadata-Version: 2.4
Name: ommx_dwave_adapter
Version: 0.1.1
Summary: An adapter between OMMX and DWave
Author-email: "Jij Inc." <info@j-ij.com>
Classifier: Programming Language :: Python :: 3 :: Only
Classifier: Programming Language :: Python :: 3.9
Classifier: Programming Language :: Python :: 3.10
Classifier: Programming Language :: Python :: 3.11
Classifier: Programming Language :: Python :: 3.12
Classifier: License :: OSI Approved :: Apache Software License
Requires-Python: >=3.9
License-File: LICENSE
Requires-Dist: ommx<3.0.0,>=2.0.3
Requires-Dist: dwave-system>=1.29.1
Provides-Extra: dev
Requires-Dist: pyright; extra == "dev"
Requires-Dist: pytest; extra == "dev"
Requires-Dist: ruff; extra == "dev"
Requires-Dist: sphinx; extra == "dev"
Requires-Dist: sphinx-autoapi; extra == "dev"
Requires-Dist: sphinx_fontawesome; extra == "dev"
Requires-Dist: sphinx_rtd_theme; extra == "dev"
Dynamic: license-file
